trio_serial/__init__.py
trio_serial/abstract.py
trio_serial/bsd.py
trio_serial/cygwin.py
trio_serial/darwin.py
trio_serial/linux.py
trio_serial/posix.py
trio_serial/py.typed
trio_serial-0.4.0.dist-info/LICENSE
trio_serial-0.4.0.dist-info/METADATA
trio_serial-0.4.0.dist-info/WHEEL
trio_serial-0.4.0.dist-info/RECORD
